Primos/__init__.py
Primosp-1.0.dist-info/LICENSE.txt
Primosp-1.0.dist-info/METADATA
Primosp-1.0.dist-info/WHEEL
Primosp-1.0.dist-info/top_level.txt
Primosp-1.0.dist-info/RECORD
