Metadata-Version: 2.1
Name: Primosp
Version: 1.0
Summary: tool to calculate prime numbers
Home-page: UNKNOWN
Author: Eva Ruiz Macías
Author-email: evatort@gmail.com
License: GNU GPLv3
Keywords: mathematical operations
Platform: UNKNOWN
Classifier: Development Status :: 4 - Beta
Classifier: Intended Audience :: Developers
Classifier: Topic :: Utilities
Classifier: License :: OSI Approved :: GNU General Public License v3 (GPLv3)
Classifier: Programming Language :: Python :: 3
Classifier: Operating System :: OS Independent
License-File: LICENSE.txt
